LICENSE
LICENSE-MODEL
README.md
setup.py
data/__init__.py
data/combined_dataset.py
data/encodec.py
data/tokenizer.py
steps/__init__.py
steps/optim.py
steps/trainer.py
steps/trainer_utils.py
voicestar/__init__.py
voicestar/api.py
voicestar/cli.py
voicestar/utils.py
voicestar/voicestar.py
voicestar.egg-info/PKG-INFO
voicestar.egg-info/SOURCES.txt
voicestar.egg-info/dependency_links.txt
voicestar.egg-info/entry_points.txt
voicestar.egg-info/requires.txt
voicestar.egg-info/top_level.txt
voicestar/data/__init__.py
voicestar/data/encodec.py
voicestar/modules/__init__.py
voicestar/modules/activation.py
voicestar/modules/embedding.py
voicestar/modules/sampling.py
voicestar/modules/scaling.py
voicestar/modules/transformer.py
voicestar/modules/utils.py
voicestar/modules/visualizer.py
voicestar/scripts/__init__.py
voicestar/scripts/copy_codebase.py