Metadata-Version: 2.4
Name: voicestar
Version: 0.1.0
Summary: VoiceStar: Robust, Duration-Controllable TTS that can Extrapolate
Home-page: https://github.com/jasonppy/VoiceStar
Author: Puyuan Peng
License: MIT
License-File: LICENSE
License-File: LICENSE-MODEL
Requires-Dist: torch
Requires-Dist: torchaudio
Requires-Dist: numpy
Requires-Dist: tqdm
Requires-Dist: fire
Requires-Dist: phonemizer
Requires-Dist: torchmetrics
Requires-Dist: einops
Requires-Dist: omegaconf==2.3.0
Requires-Dist: openai-whisper
Requires-Dist: transformers[torch]
Requires-Dist: huggingface_hub
Requires-Dist: gradio
Requires-Dist: click
Requires-Dist: txtsplit
Provides-Extra: train
Requires-Dist: huggingface_hub; extra == "train"
Requires-Dist: datasets; extra == "train"
Requires-Dist: tensorboard; extra == "train"
Requires-Dist: wandb; extra == "train"
Requires-Dist: matplotlib; extra == "train"
Requires-Dist: ffmpeg-python; extra == "train"
Requires-Dist: scipy; extra == "train"
Requires-Dist: soundfile; extra == "train"
Dynamic: author
Dynamic: description
Dynamic: description-content-type
Dynamic: home-page
Dynamic: license
Dynamic: license-file
Dynamic: provides-extra
Dynamic: requires-dist
Dynamic: summary
